sphinx_markdown/__init__.py
sphinx_markdown/directives.py
sphinx_markdown/nodes.py
sphinx_markdown/search.py
sphinx_markdown/extensions/__init__.py
sphinx_markdown/extensions/images.py
sphinx_markdown-1.0.2.dist-info/DESCRIPTION.rst
sphinx_markdown-1.0.2.dist-info/METADATA
sphinx_markdown-1.0.2.dist-info/RECORD
sphinx_markdown-1.0.2.dist-info/WHEEL
sphinx_markdown-1.0.2.dist-info/metadata.json
sphinx_markdown-1.0.2.dist-info/top_level.txt
