Metadata-Version: 2.0
Name: sphinx-markdown
Version: 1.0.2
Summary: Sphinx extension to support Markdown files
Home-page: https://github.com/Alphadelta14/sphinx-markdown
Author: Alphadelta14
Author-email: alpha@alphaservcomputing.solutions
License: MIT
Keywords: sphinx markdown
Platform: UNKNOWN
Classifier: Development Status :: 4 - Beta
Classifier: Environment :: Plugins
Classifier: License :: OSI Approved :: MIT License
Classifier: Topic :: Documentation
Classifier: Programming Language :: Python
Classifier: Programming Language :: Python :: 2
Classifier: Programming Language :: Python :: 2.7
Classifier: Programming Language :: Python :: 3
Requires-Dist: Markdown
Requires-Dist: sphinx
